dynamodelx/__init__.py
dynamodelx/plots/__init__.py
dynamodelx/plots/tabular/__init__.py
dynamodelx/plots/tabular/plots.py
dynamodelx/plots/vision/__init__.py
dynamodelx/tabular/__init__.py
dynamodelx/tabular/UFA/__init__.py
dynamodelx/tabular/UFA/ufa.py
dynamodelx/utils/activations.py
dynamodelx/utils/custom_arch.py
dynamodelx/utils/data.py
dynamodelx/utils/device.py
dynamodelx/utils/loss.py
dynamodelx/utils/metrics.py
dynamodelx/utils/optimizer.py
dynamodelx/utils/weights_init.py
dynamodelx/vision/__init__.py
dynamodelx-0.1.1.dist-info/METADATA
dynamodelx-0.1.1.dist-info/WHEEL
dynamodelx-0.1.1.dist-info/licenses/LICENSE
dynamodelx-0.1.1.dist-info/RECORD
