Metadata-Version: 2.4
Name: dynamodelx
Version: 0.1.1
Summary: Dynamic Models for ML with Uncertainty
Project-URL: Homepage, https://github.com/mohithgundimeda/dynamodelx.git
Author-email: Mohith Gundimeda <mohithgundemeda@gmail.com>
License-File: LICENSE
Requires-Python: >=3.12
Requires-Dist: numpy>=1.20
Requires-Dist: scikit-learn>=0.24
Requires-Dist: torch>=1.10.0
Requires-Dist: typing-extensions>=4.0
Provides-Extra: plot
Requires-Dist: matplotlib; extra == 'plot'
